nfl_espn_scraper/__init__.py
nfl_espn_scraper/player.py
nfl_espn_scraper/test.py
nfl_espn_scraper/utils.py
nfl_espn_scraper-0.5.dist-info/LICENSE
nfl_espn_scraper-0.5.dist-info/METADATA
nfl_espn_scraper-0.5.dist-info/WHEEL
nfl_espn_scraper-0.5.dist-info/top_level.txt
nfl_espn_scraper-0.5.dist-info/RECORD
