Metadata-Version: 2.1
Name: nfl-espn-scraper
Version: 0.5
Summary: UNKNOWN
Home-page: https://github.com/wilt-fova/nfl_espn_scraper
Author: Wil Maltby
Author-email: wilmaltby0618@gmail.com
License: UNKNOWN
Platform: UNKNOWN
Classifier: Programming Language :: Python :: 3
Classifier: License :: OSI Approved :: MIT License
Classifier: Operating System :: OS Independent
Requires-Python: >=3.6
License-File: LICENSE
Requires-Dist: beautifulsoup4
Requires-Dist: pandas
Requires-Dist: requests
